clashapi/__init__.py
clashapi-1.4.dist-info/METADATA
clashapi-1.4.dist-info/WHEEL
clashapi-1.4.dist-info/top_level.txt
clashapi-1.4.dist-info/RECORD
