Metadata-Version: 2.1
Name: clashapi
Version: 1.4
Summary: Update IP address of Clash of Clans and/or Clash Royale API keys with token fetching
Home-page: https://github.com/roshan1337d/clashapi
Author: Roshan Dash
Author-email: roshan1337d@gmail.com
License: MIT
Keywords: coc,cr,clash of clans,clash royale,clash,royale,clan,api
Platform: UNKNOWN
Requires-Dist: requests
